im8/__init__.py
im8/main.py
im8-1.2.0.dist-info/METADATA
im8-1.2.0.dist-info/WHEEL
im8-1.2.0.dist-info/top_level.txt
im8-1.2.0.dist-info/RECORD
