Metadata-Version: 2.1
Name: im8
Version: 1.2.0
Summary: A short description of your package
Home-page: https://github.com/yourusername/your-package-name
Author: Your Name
Author-email: your.email@example.com
Classifier: Programming Language :: Python :: 3
Classifier: License :: OSI Approved :: MIT License
Classifier: Operating System :: OS Independent
Requires-Python: >=3.6
Requires-Dist: pyperclip==1.9.0
